callattendant/__init__.py
callattendant/__main__.py
callattendant/app.cfg.example
callattendant/app.py
callattendant/config.py
callattendant/common/__init__.py
callattendant/common/utils.py
callattendant/hardware/__init__.py
callattendant/hardware/indicators.py
callattendant/hardware/modem.py
callattendant/hardware/mqttindicators.py
callattendant/hardware/nullgpio.py
callattendant/messaging/__init__.py
callattendant/messaging/message.py
callattendant/messaging/voicemail.py
callattendant/resources/blocked_greeting.wav
callattendant/resources/general_greeting.wav
callattendant/resources/goodbye.wav
callattendant/resources/invalid_response.wav
callattendant/resources/please_leave_message.wav
callattendant/resources/screener_greeting.wav
callattendant/resources/thankyou_callback.wav
callattendant/screening/__init__.py
callattendant/screening/blacklist.py
callattendant/screening/calllogger.py
callattendant/screening/callscreener.py
callattendant/screening/nextcall.py
callattendant/screening/nomorobo.py
callattendant/screening/shouldianswer.py
callattendant/screening/whitelist.py
callattendant/userinterface/__init__.py
callattendant/userinterface/webapp.cfg
callattendant/userinterface/webapp.py
callattendant/userinterface/static/bar-chart.svg
callattendant/userinterface/static/chat-left-text.svg
callattendant/userinterface/static/chat-left.svg
callattendant/userinterface/static/check2-circle.svg
callattendant/userinterface/static/favicon.png
callattendant/userinterface/static/gear.svg
callattendant/userinterface/static/info-circle.svg
callattendant/userinterface/static/pencil.svg
callattendant/userinterface/static/phone-inbound.svg
callattendant/userinterface/static/play-fill.svg
callattendant/userinterface/static/play.svg
callattendant/userinterface/static/question-circle.svg
callattendant/userinterface/static/telephone-inbound.svg
callattendant/userinterface/static/telephone-x.svg
callattendant/userinterface/static/telephone.svg
callattendant-2.3.0.dist-info/LICENSE
callattendant-2.3.0.dist-info/METADATA
callattendant-2.3.0.dist-info/WHEEL
callattendant-2.3.0.dist-info/entry_points.txt
callattendant-2.3.0.dist-info/top_level.txt
callattendant-2.3.0.dist-info/RECORD
