Metadata-Version: 2.2
Name: callattendant
Version: 2.3.0
Summary: An automated call attendant and call blocker using a USR5637 or CX930xx modem
Home-page: https://thess.github.io/callattendant/
Author: Ted Hess
Author-email: thess@kitschensync.net
Classifier: Programming Language :: Python :: 3
Classifier: License :: OSI Approved :: MIT License
Classifier: Operating System :: POSIX :: Linux
Classifier: Environment :: Other Environment
Classifier: Development Status :: 5 - Production/Stable
Classifier: Framework :: Flask
Classifier: Topic :: Communications :: Telephony
Classifier: Topic :: Home Automation
Requires-Python: >=3.5
License-File: LICENSE
Requires-Dist: Flask>=3.0.1
Requires-Dist: waitress>=3.0.2
Requires-Dist: flask-paginate>=2023.10.24
Requires-Dist: beautifulsoup4>=4.12.3
Requires-Dist: requests>=2.32.4
Requires-Dist: lxml>=5.3.0
Requires-Dist: bs4>=0.0.2
Requires-Dist: soupsieve>=2.5
Requires-Dist: Werkzeug>=3.0.1
Requires-Dist: Jinja2>=3.1.3
Requires-Dist: itsdangerous>=2.1.2
Requires-Dist: MarkupSafe>=2.1.4
Requires-Dist: PyYAML>=6.0.1
Requires-Dist: blinker>=1.7.0
Requires-Dist: click>=8.1.7
Requires-Dist: pygments>=2.17.2
Requires-Dist: pyserial>=3.5
Dynamic: author
Dynamic: author-email
Dynamic: classifier
Dynamic: description
Dynamic: description-content-type
Dynamic: home-page
Dynamic: requires-dist
Dynamic: requires-python
Dynamic: summary
